allennlp_server/__init__.py
allennlp_server/version.py
allennlp_server/commands/__init__.py
allennlp_server/commands/server_simple.py
allennlp_server-1.0.0.dist-info/LICENSE
allennlp_server-1.0.0.dist-info/METADATA
allennlp_server-1.0.0.dist-info/WHEEL
allennlp_server-1.0.0.dist-info/top_level.txt
allennlp_server-1.0.0.dist-info/RECORD
