Metadata-Version: 2.1
Name: allennlp-server
Version: 1.0.0
Summary: Simple demo server for AllenNLP models and training config builder.
Home-page: https://github.com/allenai/allennlp-server
Author: Allen Institute for Artificial Intelligence
Author-email: allennlp@allenai.org
License: Apache
Keywords: allennlp simple demo server serve models configuration file NLP deep learning machine reading
Platform: UNKNOWN
Classifier: Development Status :: 5 - Production/Stable
Classifier: Framework :: Flake8
Classifier: Framework :: Flask
Classifier: Intended Audience :: Developers
Classifier: Intended Audience :: Science/Research
Classifier: License :: OSI Approved :: Apache Software License
Classifier: Programming Language :: Python
Classifier: Programming Language :: Python :: 3
Classifier: Programming Language :: Python :: 3 :: Only
Classifier: Programming Language :: Python :: 3.6
Classifier: Programming Language :: Python :: 3.7
Classifier: Programming Language :: Python :: 3.8
Classifier: Topic :: Scientific/Engineering
Classifier: Topic :: Scientific/Engineering :: Artificial Intelligence
Requires-Python: >=3.6.1
Requires-Dist: allennlp (<3.0,>=2.0)
Requires-Dist: allennlp-models (<3.0,>=2.0)
Requires-Dist: flask (>=1.0.2)
Requires-Dist: flask-cors (>=3.0.7)
Requires-Dist: gevent (>=1.3.6)
